chakula/__init__.py
chakula/__main__.py
chakula/formatter.py
chakula/main.py
chakula-0.8.0.data/scripts/chakula
chakula-0.8.0.dist-info/DESCRIPTION.rst
chakula-0.8.0.dist-info/METADATA
chakula-0.8.0.dist-info/RECORD
chakula-0.8.0.dist-info/WHEEL
chakula-0.8.0.dist-info/metadata.json
chakula-0.8.0.dist-info/top_level.txt
