Metadata-Version: 2.0
Name: chakula
Version: 0.8.0
Summary: An RSS feed monitor mimicking tail -f
Home-page: https://github.com/reubano/chakula
Author: Reuben Cummings
Author-email: reubano@gmail.com
License: BSD
Download-URL: https://github.com/reubano/chakula/archive/v0.8.0.tar.gz
Keywords: chakula,An,RSS,feed,monitor,mimicking,tail,-f
Platform: MacOS X
Platform: Windows
Platform: Linux
Classifier: License :: OSI Approved :: BSD License
Classifier: Development Status :: 3 - Alpha
Classifier: Natural Language :: English
Classifier: Programming Language :: Python :: 3
Classifier: Programming Language :: Python :: 3.5
Classifier: Programming Language :: Python :: 3.6
Classifier: Programming Language :: Python :: Implementation :: PyPy
Classifier: Environment :: Console
Classifier: Topic :: Software Development :: Libraries :: Python Modules
Classifier: Topic :: Utilities
Classifier: Framework :: Flask
Classifier: Operating System :: OS Independent
Classifier: Operating System :: POSIX :: Linux
Classifier: Operating System :: MacOS :: MacOS X
Classifier: Operating System :: Microsoft :: Windows
Requires-Dist: feedparser (>=5.2.1,<6.0.0)
Requires-Dist: pygogo (<0.10.0,>=0.9.1)
Requires-Dist: python-dateutil (<3.0.0,>=2.6.0)
Provides-Extra: develop
Requires-Dist: coverage (>=4.0.3,<5.0.0); extra == 'develop'
Requires-Dist: flake8 (<3.0.0,>=2.5.1); extra == 'develop'
Requires-Dist: manage.py (>=0.2.10,<0.3.0); extra == 'develop'
Requires-Dist: pep8 (>=1.5.7,<2.0.0); extra == 'develop'
Requires-Dist: pip (<10.0.0,>=9.0.0); extra == 'develop'
Requires-Dist: pkutils (>=0.13.6,<0.14.0); extra == 'develop'
Requires-Dist: pylint (>=1.5.2,<2.0.0); extra == 'develop'
Requires-Dist: pytest (>=3.0.6,<4.0.0); extra == 'develop'
Requires-Dist: scripttest (>=1.3,<2.0); extra == 'develop'
Requires-Dist: setuptools (<35.0.0,>=23.0.0); extra == 'develop'
Requires-Dist: tox (<3.0.0,>=2.3.1); extra == 'develop'
Requires-Dist: twine (>=1.8.1,<2.0.0); extra == 'develop'
Requires-Dist: virtualenv (>=15.1.0,<16.0.0); extra == 'develop'
Provides-Extra: redis
Requires-Dist: redisworks (>=0.2.7,<0.3.0); extra == 'redis'
